pygooglehomenotifier/__init__.py
pygooglehomenotifier/googlehomenotifier.py
PyGoogleHomeNotifier-0.1.1.dist-info/LICENSE
PyGoogleHomeNotifier-0.1.1.dist-info/METADATA
PyGoogleHomeNotifier-0.1.1.dist-info/WHEEL
PyGoogleHomeNotifier-0.1.1.dist-info/top_level.txt
PyGoogleHomeNotifier-0.1.1.dist-info/RECORD
