Metadata-Version: 2.1
Name: PyGoogleHomeNotifier
Version: 0.1.1
Summary: google-home-notifier for python
Home-page: https://github.com/k-sh/pygooglehomenotifier
Author: k-sh
Author-email: tefutefu85@gmail.com
License: MIT
Keywords: pygooglehomenotifier PyGoogleHomeNotifier
Platform: UNKNOWN
Classifier: Programming Language :: Python :: 3
Classifier: License :: OSI Approved :: MIT License
Classifier: Operating System :: OS Independent
Requires-Python: >=3.6
Requires-Dist: PyChromecast
